{"commitInfo":{"timestamp":1762433741630,"operation":"STREAMING UPDATE","operationParameters":{"outputMode":"Append","queryId":"35d82b4c-bd8c-4724-bc02-4824f5dbc672","epochId":"0"},"isolationLevel":"Serializable","isBlindAppend":true,"operationMetrics":{"numRemovedFiles":"0","numOutputRows":"0","numOutputBytes":"894","numAddedFiles":"0"},"engineInfo":"Apache-Spark/3.4.1 Delta-Lake/2.4.0","txnId":"09fb3240-982e-49d9-9c40-81172967fede"}}
{"protocol":{"minReaderVersion":1,"minWriterVersion":2}}
{"metaData":{"id":"233bf8d3-b8fe-42e3-a828-2ed0be51f130","format":{"provider":"parquet","options":{}},"schemaString":"{\"type\":\"struct\",\"fields\":[{\"name\":\"event_time\",\"type\":\"string\",\"nullable\":true,\"metadata\":{}},{\"name\":\"segment_id\",\"type\":\"string\",\"nullable\":true,\"metadata\":{}},{\"name\":\"speed_kmh\",\"type\":\"double\",\"nullable\":true,\"metadata\":{}},{\"name\":\"congestion_pct\",\"type\":\"double\",\"nullable\":true,\"metadata\":{}},{\"name\":\"source\",\"type\":\"string\",\"nullable\":true,\"metadata\":{}},{\"name\":\"event_ts\",\"type\":\"timestamp\",\"nullable\":true,\"metadata\":{\"spark.watermarkDelayMs\":600000}},{\"name\":\"ingested_at\",\"type\":\"timestamp\",\"nullable\":true,\"metadata\":{}}]}","partitionColumns":[],"configuration":{},"createdTime":1762433731343}}
{"txn":{"appId":"35d82b4c-bd8c-4724-bc02-4824f5dbc672","version":0,"lastUpdated":1762433741624}}
